causum/__init__.py
causum/cache.py
causum/client.py
causum/config.py
causum/exceptions.py
causum/adapters/__init__.py
causum/adapters/base.py
causum/adapters/clickhouse.py
causum/adapters/mongodb.py
causum/adapters/mysql.py
causum/adapters/postgres.py
causum/adapters/sqlalchemy_adapter.py
causum/adapters/timescaledb.py
causum/examples/direct_queries.py
causum/examples/prompt_usage.py
causum/examples/sqlalchemy_databases.py
causum/examples/standalone.py
causum/examples/test_mongo_connection.py
causum/governance/__init__.py
causum/governance/client.py
causum/governance/metadata.py
causum/parsers/__init__.py
causum/parsers/mongo_parser.py
causum/parsers/sql_parser.py
causum/tests/__init__.py
causum-0.1.0.dist-info/licenses/LICENSE
causum-0.1.0.dist-info/METADATA
causum-0.1.0.dist-info/WHEEL
causum-0.1.0.dist-info/top_level.txt
causum-0.1.0.dist-info/RECORD
