Metadata-Version: 2.4
Name: causum
Version: 0.1.0
Summary: Causum™ API client for RAG/data systems with built-in governance and metadata capture
Author-email: Causum <support@causum.ai>
License: MIT
Project-URL: Homepage, https://gitlab.com/causum/causum-py.git
Project-URL: Documentation, https://gitlab.com/causum/causum-py.git#readme
Project-URL: Repository, https://gitlab.com/causum/causum-py.git
Project-URL: Issues, https://gitlab.com/causum/causum-py.git/issues
Keywords: causum,api,rag,langchain,llamaindex,governance,metadata
Classifier: Development Status :: 3 - Alpha
Classifier: Intended Audience :: Developers
Classifier: License :: OSI Approved :: MIT License
Classifier: Programming Language :: Python :: 3
Classifier: Programming Language :: Python :: 3.9
Classifier: Programming Language :: Python :: 3.10
Classifier: Programming Language :: Python :: 3.11
Classifier: Programming Language :: Python :: 3.12
Classifier: Topic :: Database
Classifier: Topic :: Software Development :: Libraries :: Python Modules
Requires-Python: >=3.9
License-File: LICENSE
Requires-Dist: pydantic>=2.0
Requires-Dist: psycopg2-binary>=2.9
Requires-Dist: asyncpg>=0.29
Requires-Dist: mysql-connector-python>=8.0
Requires-Dist: clickhouse-driver>=0.2
Requires-Dist: pymongo>=4.0
Requires-Dist: motor>=3.0
Requires-Dist: sqlglot>=20.0
Requires-Dist: httpx>=0.25
Requires-Dist: diskcache>=5.6
Requires-Dist: python-dotenv>=1.0
Requires-Dist: sqlalchemy>=2.0
Provides-Extra: langchain
Requires-Dist: langchain>=0.1.0; extra == "langchain"
Provides-Extra: llamaindex
Requires-Dist: llama-index>=0.9.0; extra == "llamaindex"
Provides-Extra: all
Requires-Dist: langchain>=0.1.0; extra == "all"
Requires-Dist: llama-index>=0.9.0; extra == "all"
Provides-Extra: dev
Requires-Dist: pytest>=7.0; extra == "dev"
Requires-Dist: pytest-asyncio>=0.21; extra == "dev"
Requires-Dist: black>=23.0; extra == "dev"
Requires-Dist: ruff>=0.1.0; extra == "dev"
Requires-Dist: mypy>=1.0; extra == "dev"
Dynamic: license-file
